{
  "objectives": {
    "general": "Aportar a estudiantes y profesionalistas los fundamentos teóricos de las redes neuronales artificiales a fin adquirir habilidades que eventualmente puedan servir para proponer variantes o complementos competitivos con los modelos matemáticos ya existentes.",
    "specific": [
      {
        "icon": "brain",
        "title": "Desarrollo de Modelos Matemáticos",
        "description": "Inculcar el interés por el desarrollo de modelos matemáticos relacionados a las redes neuronales artificiales."
      },
      {
        "icon": "chart",
        "title": "Análisis y Procesamiento de Datos",
        "description": "Fortalecer la habilidad para recopilar información relacionada a la resolución de problemas de procesamiento y clasificación de datos."
      },
      {
        "icon": "code",
        "title": "Verificación con Programación",
        "description": "Desarrollar la habilidad para verificar el análisis matemático utilizando lenguajes de programación."
      },
      {
        "icon": "team",
        "title": "Trabajo Colaborativo",
        "description": "Practicar la colaboración para el entendimiento y resolución de problemas de análisis y clasificación de datos."
      },
      {
        "icon": "presentation",
        "title": "Comunicación Efectiva",
        "description": "Enseñar a comunicar y difundir efectivamente las estrategias propuestas para la resolución de problemas matemáticos."
      }
    ]
  }
}